tilsit_i18n/__init__.py
tilsit_i18n/py.typed
tilsit_i18n-1.0.0.dist-info/WHEEL
tilsit_i18n-1.0.0.dist-info/METADATA
tilsit_i18n-1.0.0.dist-info/RECORD
