Metadata-Version: 2.3
Name: tilsit-i18n
Version: 1.0.0
Summary: Translation services
Author: Rafal Padkowski
Author-email: Rafal Padkowski <rafaelp@poczta.onet.pl>
Requires-Dist: loguru>=0.7.3
Requires-Python: >=3.13
